EC312/__init__.py
EC312/machinelearning.py
machine_learning_staps/__init__.py
machine_learning_staps/machinelearning.py
ec312-0.5.dist-info/METADATA
ec312-0.5.dist-info/WHEEL
ec312-0.5.dist-info/top_level.txt
ec312-0.5.dist-info/RECORD
